{
    "status_code": 200,
    "data": {
        "Table": {
            "AttributeDefinitions": [
                {
                    "AttributeName": "test",
                    "AttributeType": "S"
                }
            ],
            "TableName": "test",
            "KeySchema": [
                {
                    "AttributeName": "test",
                    "KeyType": "HASH"
                }
            ],
            "TableStatus": "ACTIVE",
            "CreationDateTime": {
                "__class__": "datetime",
                "year": 2020,
                "month": 7,
                "day": 25,
                "hour": 9,
                "minute": 26,
                "second": 8,
                "microsecond": 90000
            },
            "ProvisionedThroughput": {
                "NumberOfDecreasesToday": 0,
                "ReadCapacityUnits": 5,
                "WriteCapacityUnits": 5
            },
            "TableSizeBytes": 0,
            "ItemCount": 0,
            "TableArn": "arn:aws:dynamodb:eu-west-1:000000000000:table/test",
            "TableId": "4e84c68c-1500-403c-8e85-446327f3fa47"
        },
        "ResponseMetadata": {
            "RequestId": "TMO5DNFOVDKM11CBJ0F30OF11BVV4KQNSO5AEMVJF66Q9ASUAAJG",
            "HTTPStatusCode": 200,
            "HTTPHeaders": {
                "server": "Server",
                "date": "Mon, 27 Jul 2020 07:39:34 GMT",
                "content-type": "application/x-amz-json-1.0",
                "content-length": "458",
                "connection": "keep-alive",
                "x-amzn-requestid": "TMO5DNFOVDKM11CBJ0F30OF11BVV4KQNSO5AEMVJF66Q9ASUAAJG",
                "x-amz-crc32": "3254700394"
            },
            "RetryAttempts": 0
        }
    }
}
